quick_rabbit/__init__.py
quick_rabbit/core.py
quick_rabbit/utils.py
quick_rabbit-0.0.13.dist-info/LICENSE
quick_rabbit-0.0.13.dist-info/METADATA
quick_rabbit-0.0.13.dist-info/WHEEL
quick_rabbit-0.0.13.dist-info/top_level.txt
quick_rabbit-0.0.13.dist-info/RECORD
