Metadata-Version: 2.1
Name: quick-rabbit
Version: 0.0.13
Summary: Library to use Rabbit MQ in a quick and easy way
Home-page: https://github.com/Kevinbourdal/quick_rabbit
Author: Kevin Lopez Bourdal
Author-email: kevin.bourdal@outlook.com
License: MIT
Project-URL: Source, https://github.com/Kevinbourdal/quick_rabbit
License-File: LICENSE
Requires-Dist: pika
Requires-Dist: simplejson
